LICENSE
pypers/formatters.py
pypers/image_tools.py
pypers/mongo_helpers.py
pypers/namespace.py
pypers/url_helpers.py
pypers/video_tools.py
pypers-1.3.4.dist-info/LICENSE
pypers-1.3.4.dist-info/WHEEL
pypers-1.3.4.dist-info/METADATA
pypers-1.3.4.dist-info/RECORD
