Metadata-Version: 2.1
Name: pypers
Version: 1.3.4
Summary: A utilities module made for personal use, has small snippets which I use in many projects.
Home-page: https://pypers.divkix.me
License: MIT
Keywords: pypers,divkix helpers,python helpers,py helpers
Author: Divkix
Author-email: divkix@divkix.me
Requires-Python: >=3.7,<4.0
Classifier: Development Status :: 5 - Production/Stable
Classifier: License :: OSI Approved :: MIT License
Classifier: Natural Language :: English
Classifier: Operating System :: OS Independent
Classifier: Programming Language :: Python :: 3
Classifier: Programming Language :: Python :: 3.7
Classifier: Programming Language :: Python :: 3.8
Classifier: Programming Language :: Python :: 3.9
Classifier: Programming Language :: Python :: 3.10
Classifier: Programming Language :: Python :: 3.11
Classifier: Programming Language :: Python :: 3
Classifier: Programming Language :: Python :: Implementation :: CPython
Classifier: Topic :: Software Development :: Libraries
Classifier: Topic :: Software Development :: Libraries :: Python Modules
Classifier: Topic :: Utilities
Requires-Dist: Pillow (>=9.2.0,<10.0.0)
Requires-Dist: aiohttp (>=3.8.1,<4.0.0)
Requires-Dist: dnspython (>=2.2.1,<3.0.0)
Requires-Dist: hachoir (>=3.1.3,<4.0.0)
Requires-Dist: httpx (>=0.22,<0.24)
Requires-Dist: motor (>=3.0.0,<4.0.0)
Project-URL: Bug Tracker, https://github.com/Divkix/pypers/issues
Project-URL: Community, https://t.me/DivideProjects
Project-URL: Repository, https://github.com/Divkix/pypers
